redis_connect/__init__.py
redis_connect/connect.py
redis_connect-0.0.1.dist-info/LICENSE
redis_connect-0.0.1.dist-info/METADATA
redis_connect-0.0.1.dist-info/WHEEL
redis_connect-0.0.1.dist-info/top_level.txt
redis_connect-0.0.1.dist-info/RECORD
