Metadata-Version: 2.1
Name: redis-connect
Version: 0.0.1
Summary: Dynamic connection to redis
Author: Sabari T
Author-email: <sabariit.t@gmail.com
Keywords: python,redis,sentinel
Classifier: Development Status :: 1 - Planning
Classifier: Intended Audience :: Developers
Classifier: Programming Language :: Python :: 3
Classifier: Operating System :: Unix
Classifier: Operating System :: MacOS :: MacOS X
Classifier: Operating System :: Microsoft :: Windows
License-File: LICENSE
Requires-Dist: redis
